{
  "context_budget": {
    "samples": [
      {
        "ts": "2026-03-16T07:55:13.597276+00:00",
        "hes": 0.242,
        "wpm": 26.0,
        "state": "neutral",
        "rework": "ok"
      },
      {
        "ts": "2026-03-16T07:55:16.316234+00:00",
        "hes": 0.271,
        "wpm": 26.7,
        "state": "restructuring",
        "rework": "miss"
      },
      {
        "ts": "2026-03-16T07:55:18.221137+00:00",
        "hes": 0.235,
        "wpm": 25.4,
        "state": "hesitant",
        "rework": "ok"
      },
      {
        "ts": "2026-03-16T07:55:18.953122+00:00",
        "hes": 0.235,
        "wpm": 25.4,
        "state": "hesitant",
        "rework": "ok"
      },
      {
        "ts": "2026-03-16T07:55:19.841403+00:00",
        "hes": 0.235,
        "wpm": 25.4,
        "state": "hesitant",
        "rework": "ok"
      },
      {
        "ts": "2026-03-16T07:55:20.793944+00:00",
        "hes": 0.309,
        "wpm": 25.3,
        "state": "abandoned",
        "rework": "ok"
      },
      {
        "ts": "2026-03-16T08:20:15.853576+00:00",
        "hes": 1.0,
        "wpm": 1398.0,
        "state": "frustrated",
        "rework": "ok"
      },
      {
        "ts": "2026-03-16T08:20:56.076727+00:00",
        "hes": 0.3,
        "wpm": 400.0,
        "state": "restructuring",
        "rework": "ok"
      },
      {
        "ts": "2026-03-16T08:21:56.469869+00:00",
        "hes": 1.0,
        "wpm": 400.0,
        "state": "frustrated",
        "rework": "ok"
      }
    ],
    "avg_hes": 0.425,
    "avg_wpm": 261.4,
    "miss_count": 1,
    "total": 9
  },
  "import_rewriter": {
    "samples": [
      {
        "ts": "2026-03-16T07:55:13.597329+00:00",
        "hes": 0.242,
        "wpm": 26.0,
        "state": "neutral",
        "rework": "ok"
      },
      {
        "ts": "2026-03-16T07:55:16.316387+00:00",
        "hes": 0.271,
        "wpm": 26.7,
        "state": "restructuring",
        "rework": "miss"
      },
      {
        "ts": "2026-03-16T07:55:18.221191+00:00",
        "hes": 0.235,
        "wpm": 25.4,
        "state": "hesitant",
        "rework": "ok"
      },
      {
        "ts": "2026-03-16T07:55:18.953184+00:00",
        "hes": 0.235,
        "wpm": 25.4,
        "state": "hesitant",
        "rework": "ok"
      },
      {
        "ts": "2026-03-16T07:55:19.841472+00:00",
        "hes": 0.235,
        "wpm": 25.4,
        "state": "hesitant",
        "rework": "ok"
      },
      {
        "ts": "2026-03-16T07:55:20.793998+00:00",
        "hes": 0.309,
        "wpm": 25.3,
        "state": "abandoned",
        "rework": "ok"
      },
      {
        "ts": "2026-03-16T08:20:15.853608+00:00",
        "hes": 1.0,
        "wpm": 1398.0,
        "state": "frustrated",
        "rework": "ok"
      },
      {
        "ts": "2026-03-16T08:20:56.076769+00:00",
        "hes": 0.3,
        "wpm": 400.0,
        "state": "restructuring",
        "rework": "ok"
      },
      {
        "ts": "2026-03-16T08:21:56.469917+00:00",
        "hes": 1.0,
        "wpm": 400.0,
        "state": "frustrated",
        "rework": "ok"
      }
    ],
    "avg_hes": 0.425,
    "avg_wpm": 261.4,
    "miss_count": 1,
    "total": 9
  },
  "file_writer": {
    "samples": [
      {
        "ts": "2026-03-16T07:55:13.597354+00:00",
        "hes": 0.242,
        "wpm": 26.0,
        "state": "neutral",
        "rework": "ok"
      },
      {
        "ts": "2026-03-16T07:55:16.316420+00:00",
        "hes": 0.271,
        "wpm": 26.7,
        "state": "restructuring",
        "rework": "miss"
      },
      {
        "ts": "2026-03-16T07:55:18.221213+00:00",
        "hes": 0.235,
        "wpm": 25.4,
        "state": "hesitant",
        "rework": "ok"
      },
      {
        "ts": "2026-03-16T07:55:18.953218+00:00",
        "hes": 0.235,
        "wpm": 25.4,
        "state": "hesitant",
        "rework": "ok"
      },
      {
        "ts": "2026-03-16T07:55:19.841509+00:00",
        "hes": 0.235,
        "wpm": 25.4,
        "state": "hesitant",
        "rework": "ok"
      },
      {
        "ts": "2026-03-16T07:55:20.794017+00:00",
        "hes": 0.309,
        "wpm": 25.3,
        "state": "abandoned",
        "rework": "ok"
      },
      {
        "ts": "2026-03-16T08:20:15.853620+00:00",
        "hes": 1.0,
        "wpm": 1398.0,
        "state": "frustrated",
        "rework": "ok"
      },
      {
        "ts": "2026-03-16T08:20:56.076788+00:00",
        "hes": 0.3,
        "wpm": 400.0,
        "state": "restructuring",
        "rework": "ok"
      },
      {
        "ts": "2026-03-16T08:21:56.469939+00:00",
        "hes": 1.0,
        "wpm": 400.0,
        "state": "frustrated",
        "rework": "ok"
      }
    ],
    "avg_hes": 0.425,
    "avg_wpm": 261.4,
    "miss_count": 1,
    "total": 9
  }
}